folder_compiler_static_website/__init__.py
folder_compiler_static_website/bibtex_processor.py
folder_compiler_static_website/html_processor.py
folder_compiler_static_website/jinja_processor.py
folder_compiler_static_website/markdown_processor.py
folder_compiler_static_website-0.1.4.dist-info/LICENSE
folder_compiler_static_website-0.1.4.dist-info/METADATA
folder_compiler_static_website-0.1.4.dist-info/WHEEL
folder_compiler_static_website-0.1.4.dist-info/top_level.txt
folder_compiler_static_website-0.1.4.dist-info/RECORD
