Metadata-Version: 2.1
Name: folder-compiler-static-website
Version: 0.1.4
Summary: A simple util for 'compiling' a folder, e.g. to a static website.
Home-page: https://github.com/d-krupke/folder_compiler_static_website
Author: Dominik Krupke
Author-email: krupked@gmail.com
License: UNKNOWN
Platform: UNKNOWN
Classifier: Programming Language :: Python :: 3
Classifier: License :: OSI Approved :: MIT License
Classifier: Operating System :: OS Independent
Requires-Python: >=3.6
Requires-Dist: folder-compiler
Requires-Dist: jinja2
Requires-Dist: markdown2
Requires-Dist: bibtexparser
